operate/__init__.py
operate/config.py
operate/exceptions.py
operate/main.py
operate/operate.py
operate/models/__init__.py
operate/models/apis.py
operate/models/prompts.py
operate/models/weights/__init__.py
operate/models/weights/best.pt
operate/utils/__init__.py
operate/utils/label.py
operate/utils/misc.py
operate/utils/ocr.py
operate/utils/operating_system.py
operate/utils/screenshot.py
operate/utils/style.py
hanzo_operator-0.0.2.dist-info/LICENSE
hanzo_operator-0.0.2.dist-info/METADATA
hanzo_operator-0.0.2.dist-info/WHEEL
hanzo_operator-0.0.2.dist-info/entry_points.txt
hanzo_operator-0.0.2.dist-info/top_level.txt
hanzo_operator-0.0.2.dist-info/RECORD
