Metadata-Version: 2.2
Name: hanzo-operator
Version: 0.0.2
Summary: A framework to enable multimodal models to operate a computer
Home-page: https://github.com/yourusername/hanzo-operator
Author: Hanzo AI
Author-email: your.email@example.com
Classifier: Programming Language :: Python :: 3
Classifier: License :: OSI Approved :: MIT License
Classifier: Operating System :: OS Independent
Requires-Python: >=3.8
License-File: LICENSE
Requires-Dist: openai>=1.12.0
Requires-Dist: Pillow>=10.0.0
Requires-Dist: PyAutoGUI>=0.9.54
Requires-Dist: python-dotenv>=1.0.0
Requires-Dist: easyocr>=1.7.1
Requires-Dist: google-generativeai>=0.3.2
Requires-Dist: anthropic>=0.18.1
Requires-Dist: ollama>=0.1.7
Requires-Dist: numpy>=1.24.3
Requires-Dist: matplotlib>=3.7.1
Requires-Dist: requests>=2.31.0
Requires-Dist: torch>=2.0.1
Requires-Dist: torchvision>=0.15.2
Requires-Dist: ultralytics>=8.0.196
Dynamic: author
Dynamic: author-email
Dynamic: classifier
Dynamic: description
Dynamic: description-content-type
Dynamic: home-page
Dynamic: requires-dist
Dynamic: requires-python
Dynamic: summary
